flixbus/__init__.py
flixbus/connection.py
flixbus/flixbus.py
flixbus/flixbusbase.py
flixbus/setup.cfg
flixbus-1.0.6.dist-info/METADATA
flixbus-1.0.6.dist-info/WHEEL
flixbus-1.0.6.dist-info/licenses/LICENSE
flixbus-1.0.6.dist-info/RECORD
