Metadata-Version: 2.1
Name: flixbus
Version: 1.0.6
Summary: A Flixbus API package with easy to use high-level functions.
Project-URL: Homepage, https://gitlab.com/jeroenvb3/flixbuspip
Project-URL: Bug Tracker, https://gitlab.com/jeroenvb3/flixbuspip/-/issues
Author-email: Jeroen van Bennekum <jeroen_-@live.nl>
License-File: LICENSE
Classifier: License :: OSI Approved :: GNU Affero General Public License v3
Classifier: Operating System :: OS Independent
Classifier: Programming Language :: Python :: 3
Requires-Python: >=3.7
Requires-Dist: beautifulsoup4
Requires-Dist: requests
Requires-Dist: requests-cache
